{
  "success": true,
  "message": "laundry cleaner data",
  "data": [
    {
      "id": 511,
      "image": "https://media.istockphoto.com/id/1092103792/photo/woman-with-ironed-clothes-in-the-laundry.webp?s=2048x2048&w=is&k=20&c=mTEy31pX4jV1572giEvtvRL0yCUT8T1ceBWB3Ttswac=",
      "title": "Professional Laundry Service",
      "provider_id": 32,
      "description": "Expert laundry cleaning services.",
      "rating": 4.7,
      "price": 25,
      "discounted_price": 20,
      "offer": 20
    },
    {
      "id": 512,
      "image": "https://media.istockphoto.com/id/1503953544/photo/modern-professional-washing-vacuum-cleaner-for-upholstered-furniture-on-a-black-background.webp?s=2048x2048&w=is&k=20&c=fi86LCN_9ek_hVPkSw1d14xT5pzMYxvEMqjKVpausXg=",
      "title": "Dry Cleaning Solutions",
      "provider_id": 33,
      "description": "High-quality dry cleaning services.",
      "rating": 4.9,
      "price": 30,
      "discounted_price": 25,
      "offer": 17
    },
    {
      "id": 513,
      "image": "https://media.istockphoto.com/id/1132394829/photo/woman-delivering-dry-cleaned-clothes.webp?s=2048x2048&w=is&k=20&c=_vW6IEiRYsEyYBCyXnY5bODGX6gm7OfhcHtjHnKbxws=",
      "title": "Laundry Pickup & Delivery",
      "provider_id": 34,
      "description": "Convenient laundry pickup and delivery.",
      "rating": 4.8,
      "price": 20,
      "discounted_price": 18,
      "offer": 10
    },
    {
      "id": 514,
      "image": "https://media.istockphoto.com/id/1312638746/photo/kids-and-dad-folding-laundry-together.webp?s=2048x2048&w=is&k=20&c=iKl33sXwDNl56SOFF_j4tJpdwwOvTmTJnjioXduurW8=",
      "title": "Eco-Friendly Laundry",
      "provider_id": 35,
      "description": "Environmentally friendly laundry services.",
      "rating": 4.6,
      "price": 28,
      "discounted_price": 24,
      "offer": 15
    },
    {
      "id": 515,
      "image": "https://media.istockphoto.com/id/1368091437/photo/young-woman-ironing-close-up.webp?s=2048x2048&w=is&k=20&c=ODPBzRgWzIfjEo22UVqDRPEToJL6kNu8Djf-Oc3NhjU=",
      "title": "Laundry & Ironing",
      "provider_id": 36,
      "description": "Laundry and ironing services for your convenience.",
      "rating": 4.7,
      "price": 22,
      "discounted_price": 20,
      "offer": 10
    },
    {
      "id": 516,
      "image": "https://media.istockphoto.com/id/1134322251/photo/at-laundromat.webp?s=2048x2048&w=is&k=20&c=6rfdDYWBUg0IJcwgSc9qLASgpGgnJfYwzAZRL7K27lg=",
      "title": "Same-Day Laundry",
      "provider_id": 37,
      "description": "Quick and efficient same-day laundry.",
      "rating": 4.8,
      "price": 35,
      "discounted_price": 30,
      "offer": 14
    },
    {
      "id": 517,
      "image": "https://media.istockphoto.com/id/1329135522/photo/stack-of-folded-clean-sheets-surgical-clothes-and-industrial-iron-in-an-industrial-laundry.webp?s=2048x2048&w=is&k=20&c=vkUkD1838gLxTv1Rql9Wg7tIil1HvMEIEw6_uot3aUI=",
      "title": "Laundry for Businesses",
      "provider_id": 38,
      "description": "Commercial laundry solutions for businesses.",
      "rating": 4.7,
      "price": 40,
      "discounted_price": 35,
      "offer": 12
    },
    {
      "id": 518,
      "image": "https://media.istockphoto.com/id/1350817454/photo/worker-removing-dirt-from-carpet-indoors-closeup-cleaning-service.webp?s=2048x2048&w=is&k=20&c=VFZVCegIEyTzlQC059P-TMRQzOq8gmIqg3r8ysPPs3Q=",
      "title": "Professional Stain Removal",
      "provider_id": 41,
      "description": "Specialized stain removal services.",
      "rating": 4.8,
      "price": 22,
      "discounted_price": 19,
      "offer": 14
    }
  ]
}